django_slugify_processor/__about__.py
django_slugify_processor/__init__.py
django_slugify_processor/py.typed
django_slugify_processor/text.py
django_slugify_processor/templatetags/__init__.py
django_slugify_processor/templatetags/slugify_processor.py
django_slugify_processor-1.9.0.dist-info/METADATA
django_slugify_processor-1.9.0.dist-info/WHEEL
django_slugify_processor-1.9.0.dist-info/licenses/LICENSE
django_slugify_processor-1.9.0.dist-info/RECORD
