Metadata-Version: 2.4
Name: django-slugify-processor
Version: 1.9.0
Summary: pipeline for slugification edgecases in django
Project-URL: Bug Tracker, https://github.com/tony/django-slugify-processor/issues
Project-URL: Documentation, https://django-slugify-processor.git-pull.com
Project-URL: Repository, https://github.com/tony/django-slugify-processor
Project-URL: Changes, https://github.com/tony/django-slugify-processor/blob/master/CHANGES
Author-email: Tony Narlock <tony@git-pull.com>
License: MIT
License-File: LICENSE
Keywords: django,slug,text
Classifier: Development Status :: 5 - Production/Stable
Classifier: Environment :: Web Environment
Classifier: Framework :: Django
Classifier: Framework :: Django :: 4.2
Classifier: Framework :: Django :: 5.0
Classifier: Framework :: Django :: 5.1
Classifier: Intended Audience :: Developers
Classifier: License :: OSI Approved :: MIT License
Classifier: Operating System :: OS Independent
Classifier: Programming Language :: Python
Classifier: Programming Language :: Python :: 3
Classifier: Programming Language :: Python :: 3.9
Classifier: Programming Language :: Python :: 3.10
Classifier: Programming Language :: Python :: 3.11
Classifier: Programming Language :: Python :: 3.12
Classifier: Programming Language :: Python :: 3.13
Classifier: Programming Language :: Python :: Implementation :: CPython
Classifier: Programming Language :: Python :: Implementation :: PyPy
Classifier: Topic :: Utilities
Classifier: Typing :: Typed
Requires-Python: <4.0,>=3.9
Requires-Dist: django>=4.2
Provides-Extra: django-extensions
Requires-Dist: django-extensions; extra == 'django-extensions'
